{
  "schemaVersion": 1,
  "id": "puzzle-blocks",
  "version": "${version}",

  "name": "Puzzle Blocks",
  "description": "Lets resourcepacks change render layers of blocks",
  "authors": [
    "Motschen",
    "TeamMidnightDust"
  ],
  "contact": {
    "homepage": "https://www.midnightdust.eu/",
    "sources": "https://github.com/TeamMidnightDust/Puzzle",
    "issues": "https://github.com/TeamMidnightDust/Puzzle/issues"
  },

  "license": "MIT",
  "icon": "assets/puzzle/icon.png",

  "environment": "client",
  "entrypoints": {
    "client": [
      "net.puzzlemc.blocks.PuzzleBlocks"
    ]
  },
  "custom": {
    "modmenu": {
      "parent": "puzzle"
    }
  },

  "depends": {
    "fabric": "*"
  }
}
